xman/__init__.py
xman/__main__.py
xman/cache.py
xman/config.py
xman/extension.py
xman/handler.py
xman/header.py
xman/main.py
xman/proxy.py
xman/request.py
xman/response.py
xman/setup.py
xman/transform.py
xman/version.py
x_man-0.2.2.dist-info/LICENSE
x_man-0.2.2.dist-info/METADATA
x_man-0.2.2.dist-info/WHEEL
x_man-0.2.2.dist-info/entry_points.txt
x_man-0.2.2.dist-info/top_level.txt
x_man-0.2.2.dist-info/RECORD
