Metadata-Version: 2.1
Name: x-man
Version: 0.2.2
Summary: HTTP proxy recording & replaying requests
Home-page: https://github.com/igrek51/xman
Author: igrek51
Author-email: igrek51.dev@gmail.com
License: MIT
Platform: UNKNOWN
Classifier: Programming Language :: Python :: 3
Classifier: License :: OSI Approved :: MIT License
Classifier: Operating System :: OS Independent
Requires-Python: >=3.6.0
Requires-Dist: dataclasses
Requires-Dist: nuclear
Requires-Dist: requests
Requires-Dist: urllib3
